Hat-0.1.9.dev0.dist-info/DESCRIPTION.rst
Hat-0.1.9.dev0.dist-info/METADATA
Hat-0.1.9.dev0.dist-info/RECORD
Hat-0.1.9.dev0.dist-info/WHEEL
Hat-0.1.9.dev0.dist-info/metadata.json
Hat-0.1.9.dev0.dist-info/top_level.txt
hat/__init__.py
hat/activations.py
hat/augmentation.py
hat/callbacks.py
hat/data_transformations.py
hat/generators.py
hat/globals.py
hat/initializations.py
hat/metrics.py
hat/models.py
hat/objectives.py
hat/optimizers.py
hat/preprocessing.py
hat/regularizations.py
hat/serializations.py
hat/supports.py
hat/backend/__init__.py
hat/backend/theano_backend.py
hat/layers/__init__.py
hat/layers/cnn.py
hat/layers/core.py
hat/layers/embeddings.py
hat/layers/noise.py
hat/layers/normalization.py
hat/layers/pool.py
hat/layers/pooling.py
hat/layers/radial_basis.py
hat/layers/rnn.py
hat/layers/your_layer.py
hat/utils/__init__.py
hat/utils/plots.py
