Metadata-Version: 2.0
Name: Hat
Version: 0.1.9.dev0
Summary: Deep learning toolbox built on Theano
Home-page: https://github.com/qiuqiangkong/Hat
Author: Qiuqiang Kong
Author-email: qiuqiangkong@gmail.com
License: MIT
Platform: UNKNOWN
